perennityai_mp_extract/__init__.py
perennityai_mp_extract/main.py
perennityai_mp_extract/data_extraction/__init__.py
perennityai_mp_extract/data_extraction/data_extractor.py
perennityai_mp_extract/utils/__init__.py
perennityai_mp_extract/utils/csv_handler.py
perennityai_mp_extract/utils/feature_header.py
perennityai_mp_extract/utils/logger.py
perennityai_mp_extract/utils/tfrecord_processor.py
perennityai_mp_extract-0.1.0.dist-info/LICENSE
perennityai_mp_extract-0.1.0.dist-info/METADATA
perennityai_mp_extract-0.1.0.dist-info/WHEEL
perennityai_mp_extract-0.1.0.dist-info/entry_points.txt
perennityai_mp_extract-0.1.0.dist-info/top_level.txt
perennityai_mp_extract-0.1.0.dist-info/RECORD
