Metadata-Version: 2.1
Name: perennityai-mp-extract
Version: 0.1.0
Summary: A tool for extracting gesture landmarks and metadata from videos and saving them to disk using MediaPipe.
Home-page: https://github.com/perennityai/perennityai-mp-extract
Author: Perennity AI
Author-email: Perennity AI <info@perennityai.com>
License: MIT License
Project-URL: Homepage, https://github.com/perennityai/perennityai-mp-extract
Project-URL: Documentation, https://github.com/perennityai/perennityai-mp-extract/blob/main/README.md
Project-URL: Issue Tracker, https://github.com/perennityai/perennityai-mp-extract/issues
Keywords: mediapipe,data visualization,landmarks,pose,AI
Classifier: Development Status :: 3 - Alpha
Classifier: Intended Audience :: Developers
Classifier: License :: OSI Approved :: MIT License
Classifier: Programming Language :: Python :: 3
Classifier: Programming Language :: Python :: 3.7
Classifier: Programming Language :: Python :: 3.8
Classifier: Programming Language :: Python :: 3.9
Classifier: Programming Language :: Python :: 3.10
Classifier: Topic :: Software Development :: Libraries :: Python Modules
Classifier: Topic :: Scientific/Engineering :: Artificial Intelligence
Requires-Python: >=3.8
License-File: LICENSE
Requires-Dist: tensorflow<=2.17.0,>=2.5.0
Requires-Dist: tensorboard<=2.17.0,>=2.5.0
Requires-Dist: keras
Requires-Dist: matplotlib
Requires-Dist: opencv-python
Requires-Dist: json5
Requires-Dist: pandas
Requires-Dist: mediapipe
Requires-Dist: yt-dlp
